Lab 2/Interlock/AtStateCounterTester.v
//-----------------------------------------------------------
// Module name:
// AtStateCounterTester
//
// Description:
// Module implemented as part of testing system.
// Tests all possible states of AtStateCounter.
// Tests reset.
// 
// Author(s):
// Krista Holden
//
//----------------------------------------------------------- 

module AtStateCounterTester (rst, clk, out);
	input [2:0] out;
	output reg clk, rst;

  parameter stimDelay = 20;

  always begin
    #stimDelay clk = !clk;
  end
  
  initial // Response
  begin
    $display("\t\t out \t rst \t clk \t Time ");
	$monitor("\t\t %b \t %b \t %b", out, rst, clk, $time );
  end

  initial // Stimulus
  begin
    rst = 0; clk = 0;
    #stimDelay rst = 1;
    #(64 * stimDelay) rst = 0;
    #(3 * stimDelay) rst = 1;
    #(4*stimDelay); // needed to see END of simulation
    $finish; // finish simulation
  end
endmodule

Lab 2/Interlock/flipflop.sv
//-----------------------------------------------------------
// Module name:
// DFlipFlop
//
// Description:
// Module implemented as a flip flop with active low reset.
// Includes input to clock and outputs q and qBar.
// 
// Author(s):
// Included file from EE371
//
// *NOTE: modified the always block assign statements to be
//        non-blocking statements for correct verilog usage.
//----------------------------------------------------------- 

module DFlipFlop(q,  D, clk, rst);
	input D, clk, rst;
	output q;
	reg q;
		always@ (posedge clk)
		begin  // Statements need to be non-blocking
			if(rst)
				q <= 0;
			else
				q <= D;
		end
endmodule

Lab 2/Interlock/rippleUp.v
//-----------------------------------------------------------
// Module name:
// RippleUp
//
// Description:
// Implements a 4-bit ripple up counter with reset active low
// where counting beings at 0000 and loops back after 1111
// 
// Author(s):
// Zach Nehrenberg
//
//----------------------------------------------------------- 

`include "flipflop.v"

module RippleUp(rst, clk, out);
	input clk, rst;
	output [3:0] out;
	
	wire qBar1, qBar2, qBar3, qBar4;
	
	DFlipFlop flip1(out[0], qBar1, qBar1, clk, rst);
	DFlipFlop flip2(out[1], qBar2, qBar2, qBar1, rst);
	DFlipFlop flip3(out[2], qBar3, qBar3, qBar2, rst);
	DFlipFlop flip4(out[3], qBar4, qBar4, qBar3, rst);
endmodule

Lab 2/Interlock/AtStateCounter.v
//-----------------------------------------------------------
// Module name:
// AtStateCounter
//
// Description:
// Uses a 4-bit ripple up counter with reset active low
// to track if the counter is at five, seven, or eight.
// 
// Author(s):
// Krista Holden
//
//----------------------------------------------------------- 

`include "rippleUp.v"

module AtStateCounter(rst, clk, out);
	input clk, rst;
	output [2:0] out;
	
	wire atFive, atSeven, atEight;
	wire [3:0] count;
	
	parameter five = 4'b0101;
	parameter seven = 4'b0111;
	parameter eight = 4'b1000;
	
	assign out = {atFive, atSeven, atEight};
	
	RippleUp counter(rst, clk, count);
	
	assign atFive = (count == five);
	assign atSeven = (count == seven);
	assign atEight = (count == eight);	
endmodule

Lab 2/Interlock/AtStateCounterTop.v
//-----------------------------------------------------------
// Module name:
// UserInputTop
//
// Description:
// Module implemented as part of testing system.
// Test UserInput with UserInputTester module.
// 
// Author(s):
// Krista Holden
//
//-----------------------------------------------------------

`include "AtStateCounter.v"
`include "AtStateCounterTester.v"

module AtStateCounterTop ();
  // connect the two modules
  wire clk, in;
  wire [2:0] out;

  // declare an instance of the Johnson
  AtStateCounter myAtStateCounter (rst, clk, out);

  // declare an instance of the testIt module
  AtStateCounterTester myAtStateCounterTester (rst, clk, out);

  // file for gtkwave
  initial
  begin
    $dumpfile("AtStateCounter.vcd");
    $dumpvars(1,myAtStateCounter);
  end
endmodule

Lab 2/Interlock/AtStateCounter.vcd
$date
	Tue Apr 14 17:11:53 2015
$end
$version
	Icarus Verilog
$end
$timescale
	1s
$end
$scope module AtStateCounterTop $end
$scope module myAtStateCounter $end
$var wire 1 ! atEight $end
$var wire 1 " atFive $end
$var wire 1 # atSeven $end
$var wire 1 $ clk $end
$var wire 4 % count [3:0] $end
$var wire 3 & out [2:0] $end
$var wire 1 ' rst $end
$upscope $end
$upscope $end
$enddefinitions $end
#0
$dumpvars
0'
b0 &
b0 %
0$
0#
0"
0!
$end
#20
b1 %
1'
1$
#40
0$
#60
b10 %
1$
#80
0$
#100
b11 %
1$
#120
0$
#140
b100 %
1$
#160
0$
#180
b101 %
b100 &
1"
1$
#200
0$
#220
b110 %
b0 &
0"
1$
#240
0$
#260
b111 %
b10 &
1#
1$
#280
0$
#300
1!
b1000 %
b1 &
0#
1$
#320
0$
#340
b1001 %
b0 &
0!
1$
#360
0$
#380
b1010 %
b0 &
0!
1$
#400
0$
#420
b1011 %
1$
#440
0$
#460
b0 &
0!
b1100 %
1$
#480
0$
#500
b1101 %
1$
#520
0$
#540
b1110 %
1$
#560
0$
#580
b1111 %
1$
#600
0$
#620
b0 &
0!
b0 %
1$
#640
0$
#660
b1 %
1$
#680
0$
#700
b10 %
1$
#720
0$
#740
b11 %
1$
#760
0$
#780
b100 %
1$
#800
0$
#820
b101 %
b100 &
1"
1$
#840
0$
#860
b110 %
b0 &
0"
1$
#880
0$
#900
b111 %
b10 &
1#
1$
#920
0$
#940
1!
b1000 %
b1 &
0#
1$
#960
0$
#980
b1001 %
b0 &
0!
1$
#1000
0$
#1020
b1010 %
b0 &
0!
1$
#1040
0$
#1060
b1011 %
1$
#1080
0$
#1100
b0 &
0!
b1100 %
1$
#1120
0$
#1140
b1101 %
1$
#1160
0$
#1180
b1110 %
1$
#1200
0$
#1220
b1111 %
1$
#1240
0$
#1260
b0 &
0!
b0 %
1$
#1280
0$
#1300
1$
0'
#1320
0$
#1340
1$
#1360
0$
1'
#1380
b1 %
1$
#1400
0$
#1420
b10 %
1$
