Lab 2/Interlock/countup.v
//-----------------------------------------------------------
// Module name:
// CountUp
//
// Description:
// Outputs the num seconds passed on the HEX.
// 
// Author(s):
// Krista Holden
//
//----------------------------------------------------------- 

module CountUp(count, hex);
	input  [3:0] count;
	output [6:0] hex;
	
	reg    [6:0] current;
		
	parameter c0 = 4'b0000;
	parameter c1 = 4'b0001;
	parameter c2 = 4'b0010;
	parameter c3 = 4'b0011;
	parameter c4 = 4'b0100;
	parameter c5 = 4'b0101;
	parameter c6 = 4'b0110;
	parameter c7 = 4'b0111;
	parameter c8 = 4'b1000;
	
	parameter nothing = 7'b1111111;
	parameter zero		= 7'b1000000;
	parameter one 		= 7'b1100111;
	parameter two 		= 7'b0100100;
	parameter three 	= 7'b0110000;
	parameter four 	= 7'b1000110;
	parameter five 	= 7'b0010010;
	parameter six 		= 7'b0000010;
	parameter seven 	= 7'b1111000;
	parameter eight 	= 7'b0000000;
	
	assign hex = current;
	
	initial current = nothing;
	
	always @(*) begin
		case(count)
			c0: current = one;
			c1: current = one;
			c2: current = two;
			c3: current = three;
			c4: current = four;
			c5: current = five;
			c6: current = six;
			c7: current = seven;
			c8: current = eight;
			default: current = nothing;
		endcase
	end
	
endmodule

Lab 2/Interlock/containsTester.v
//-----------------------------------------------------------
// Module name:
// CountUpTester
//
// Description:
// Module implemented as part of testing system.
// Tests all possible states of ContainsShip.
// 
// Author(s):
// Krista Holden
//
//----------------------------------------------------------- 

module ContainsShipTester (clock, reset, shipDocked, arriving, departing, openDoor);
  input shipDocked;
  output reg clock, reset, openDoor, arriving, departing;  
	
  parameter stimDelay = 20;
  
  initial clock = 0;
  
  always begin
    #stimDelay clock = !clock;
  end
  
  initial // Response
  begin
    $display("\t\t clock \t reset \t openDoor \t arriving \t departing ");
	$monitor("\t\t %b \t %b", clock, reset, openDoor, arriving, departing);
  end

  initial // Stimulus
  begin
					 openDoor = 0;	departing = 0;	arriving = 0;	reset = 1; // empty
																	reset = 0;
	
	// Departing Cycle (nothing happens)
	#(3 * stimDelay) 				departing = 1;                             
	#stimDelay 						departing = 0;
	#stimDelay 		 	 openDoor = 1;
	#stimDelay 		 	 openDoor = 0;
	
	// Arriving Cycle (empty -> enter -> contains)
	#stimDelay 										arriving = 1;
	#stimDelay 										arriving = 0;
	#stimDelay 		 	openDoor = 1;
	#stimDelay 		 	openDoor = 0;
	
	// Opening The Door (nothing happens)
	#stimDelay 		 	openDoor = 1;
	#stimDelay 		 	openDoor = 0;
	
	// Arriving Again (nothing happens)
	#stimDelay 										arriving = 1;
	#stimDelay 										arriving = 0;
	#stimDelay 		 	openDoor = 1;
	#stimDelay 		 	openDoor = 0;
	
	// Departing Cycle (contains -> exit -> empty)
	#(3 * stimDelay) 				departing = 1;                             
	#stimDelay 						departing = 0;
	#stimDelay 		 	openDoor = 1;
	#stimDelay 		 	 openDoor = 0;
	
	// Opening The Door (nothing happens)
	#stimDelay 		 	openDoor = 1;
	#stimDelay 		 	openDoor = 0;
	
	// Signal Reset @ empty
	#stimDelay 		 												reset = 1;
	#stimDelay 		 												reset = 0;
	
	// Signal Reset @ enter
	#stimDelay 										arriving = 1;
	#stimDelay 										arriving = 0;
	#stimDelay 		 												reset = 1;
	#stimDelay 		 												reset = 0;
	
	// Signal Reset @ contains
	#stimDelay 										arriving = 1;
	#stimDelay 										arriving = 0;
	#stimDelay 		 openDoor = 1;
	#stimDelay 		 openDoor = 0;
	#stimDelay 		 												reset = 1;
	#stimDelay 		 												reset = 0;
	
	// Signal Reset @ exit
	#stimDelay 										arriving = 1;
	#stimDelay 										arriving = 0;
	#stimDelay 		 	openDoor = 1;
	#stimDelay 		 	openDoor = 0;
	#(3 * stimDelay) 				departing = 1;                             
	#stimDelay 						departing = 0;
	#stimDelay 		 												reset = 1;
	#stimDelay 		 												reset = 0;
	
	 
    #(4*stimDelay); // needed to see END of simulation
    $finish; // finish simulation
  end
endmodule

Lab 2/Interlock/containsShip.v
module ContainsShip (clock, reset, shipDocked, arriving, departing, openDoor);
	input clock, reset, openDoor, arriving, departing;
	output shipDocked;
	
	reg [1:0] ps, ns;
	
	parameter empty  = 2'b00,
				 enter  = 2'b10,
				 exit   = 2'b01,
				 contains = 2'b11;
	
	initial ps = empty;
	initial ns = empty;
	
	assign shipDocked = ps[0];	

	always @(*) begin
		case(ps)
			empty: begin
				if(arriving | ns == enter)  ns = enter;
				else ns = empty;
			end
			enter: begin
				if(openDoor | ns == contains) ns = contains;
				else ns = enter;
			end
			exit: begin
				if(openDoor | ns == empty) ns = empty;
				else ns = exit;
			end
			contains: begin
				if(departing | ns == exit) ns = exit;
				else ns = contains;
			end
		endcase
	end
	
	always @(posedge clock) begin
		if(reset) ps <= empty;
		else ps <= ns;
	end
	
endmodule

Lab 2/Interlock/containsTop.v
//-----------------------------------------------------------
// Module name:
// CountUpTop
//
// Description:
// Module implemented as part of testing system.
// Test CountUp with CountUpTester module.
// 
// Author(s):
// Krista Holden
//
//-----------------------------------------------------------

`include "countup.v"
`include "countupTester.v"

module UserInputTop ();
  // connect the two modules
  wire clock, reset, shipDocked, arriving, departing, openDoor;

  // declare an instance of the Johnson
  ContainsShip myContains (clock, reset, shipDocked, arriving, departing, openDoor);

  // declare an instance of the testIt module
  ContainsShipTester myContainsTester (clock, reset, shipDocked, arriving, departing, openDoor);

  // file for gtkwave
  initial
  begin
    $dumpfile("ContainsShip.vcd");
    $dumpvars(1,myCountains);
  end
endmodule

Lab 2/Interlock/ContainsShip.vcd
$date
	Sun Apr 26 17:41:02 2015
$end
$version
	Icarus Verilog
$end
$timescale
	1s
$end
$scope module UserInputTop $end
$scope module myContains $end
$var wire 1 ! arriving $end
$var wire 1 " clock $end
$var wire 1 # departing $end
$var wire 1 $ openDoor $end
$var wire 1 % reset $end
$var wire 1 & shipDocked $end
$var reg 2 ' ns [1:0] $end
$var reg 2 ( ps [1:0] $end
$upscope $end
$upscope $end
$enddefinitions $end
#0
$dumpvars
b0 (
b0 '
0&
0%
0$
0#
0"
0!
$end
#20
1"
#40
0"
#60
1"
1#
#80
0"
0#
#100
1"
1$
#120
0"
0$
#140
b10 (
b10 '
1"
1!
#160
0"
0!
#180
1&
b11 (
b11 '
1"
1$
#200
0"
0$
#220
1"
1$
#240
0"
0$
#260
1"
1!
#280
0"
0!
#300
1"
1$
#320
0"
0$
#340
1"
#360
0"
#380
b1 (
b1 '
1"
1#
#400
0"
0#
#420
0&
b0 (
b0 '
1"
1$
#440
0"
0$
#460
1"
1$
#480
0"
0$
#500
1"
1%
#520
0"
0%
#540
b10 (
b10 '
1"
1!
#560
0"
0!
#580
b0 (
1"
1%
#600
0"
0%
#620
b10 (
1"
1!
#640
0"
0!
#660
1&
b11 (
b11 '
1"
1$
#680
0"
0$
#700
b0 '
0&
b0 (
1"
1%
#720
0"
0%
#740
b10 (
b10 '
1"
1!
#760
0"
0!
#780
1&
b11 (
b11 '
1"
1$
#800
0"
0$
#820
1"
#840
0"
#860
b1 (
b1 '
1"
1#
#880
0"
0#
#900
b0 '
0&
b0 (
1"
1%
#920
0"
0%
