Lab 2/Interlock/SynchronousUpTester.v
//-----------------------------------------------------------
// Module name:
// SynchronousUpTester
//
// Description:
// Module implemented as part of testing system.
// Tests all possible states of counter.
// Tests reset.
// 
// Author(s):
// Krista Holden
//
//----------------------------------------------------------- 

module SynchronousUpTester (rst, clk, out);
	input [3:0] out;
	output reg clk, rst;

  parameter stimDelay = 20;

  always begin
    #stimDelay clk = !clk;
  end
  
  initial // Response
  begin
    $display("\t\t out \t rst \t clk \t Time ");
	$monitor("\t\t %b \t %b \t %b", out, rst, clk, $time );
  end

  initial // Stimulus
  begin
    rst = 0; clk = 0;
    #stimDelay rst = 1;
    #(64 * stimDelay) rst = 0;
    #(3 * stimDelay) rst = 1;
    #(4*stimDelay); // needed to see END of simulation
    $finish; // finish simulation
  end
endmodule

Lab 2/Interlock/SynchronousUp.v
//-----------------------------------------------------------
// Module name:
// SynchronousUp
//
// Description:
// Module implemented as a synchronous up counter.
// Includes inputs reset and clock, and outputs the count.
// 
// Author(s):
// Krista Holden
//
//----------------------------------------------------------- 

module SynchronousUp(rst, clk, out);
	input clk, rst;
	output reg [3:0] out;
	
	parameter start = 4'b0000;
	
	initial out = start;
	
	always @(posedge clk) begin
		if(~rst) begin
			out <= start;
		end
		else begin
			out[0] <= ~out[0];
			out[1] <= out[1] ^ out[0];
			out[2] <= out[2] ^ (out[1] & out[0]);
			out[3] <= out[3] ^ (out[2] & out[1] & out[0]);
		end
	end

endmodule

Lab 2/Interlock/SynchronousUpTop.v
//-----------------------------------------------------------
// Module name:
// testBench
//
// Description:
// Module implemented as part of testing system.
// Test synchronous up counter with Tester module.
// 
// Author(s):
// Krista Holden
//-----------------------------------------------------------

`include "SynchronousUp.v"
`include "SynchronousUpTester.v"

module testBench;
	wire clk, rst;
	wire [3:0] out;
	
	//declare instance of synchronous down counter.
	SynchronousUp mySynchronousUp (rst, clk, out);

	// declare an instance of the Tester module
	SynchronousUpTester aTester (rst, clk, out);

	// generate file for gtkwave
	initial
	begin
		$dumpfile("mySynchronousUp.vcd");
		$dumpvars(1,mySynchronousUp);
	end
endmodule

Lab 2/Interlock/mySynchronousUp.vcd
$date
	Tue Apr 14 18:15:47 2015
$end
$version
	Icarus Verilog
$end
$timescale
	1s
$end
$scope module testBench $end
$scope module mySynchronousUp $end
$var wire 1 ! clk $end
$var wire 1 " rst $end
$var reg 4 # out [3:0] $end
$upscope $end
$upscope $end
$enddefinitions $end
#0
$dumpvars
b0 #
0"
0!
$end
#20
b1 #
1"
1!
#40
0!
#60
b10 #
1!
#80
0!
#100
b11 #
1!
#120
0!
#140
b100 #
1!
#160
0!
#180
b101 #
1!
#200
0!
#220
b110 #
1!
#240
0!
#260
b111 #
1!
#280
0!
#300
b1000 #
1!
#320
0!
#340
b1001 #
1!
#360
0!
#380
b1010 #
1!
#400
0!
#420
b1011 #
1!
#440
0!
#460
b1100 #
1!
#480
0!
#500
b1101 #
1!
#520
0!
#540
b1110 #
1!
#560
0!
#580
b1111 #
1!
#600
0!
#620
b0 #
1!
#640
0!
#660
b1 #
1!
#680
0!
#700
b10 #
1!
#720
0!
#740
b11 #
1!
#760
0!
#780
b100 #
1!
#800
0!
#820
b101 #
1!
#840
0!
#860
b110 #
1!
#880
0!
#900
b111 #
1!
#920
0!
#940
b1000 #
1!
#960
0!
#980
b1001 #
1!
#1000
0!
#1020
b1010 #
1!
#1040
0!
#1060
b1011 #
1!
#1080
0!
#1100
b1100 #
1!
#1120
0!
#1140
b1101 #
1!
#1160
0!
#1180
b1110 #
1!
#1200
0!
#1220
b1111 #
1!
#1240
0!
#1260
b0 #
1!
#1280
0!
#1300
1!
0"
#1320
0!
#1340
1!
#1360
0!
1"
#1380
b1 #
1!
#1400
0!
#1420
b10 #
1!
