Lab1/DownCounterSchematic/synchronousDownSchematicTester.v
//-----------------------------------------------------------
// Module name:
// SynchronousDownTester
//
// Description:
// Module implemented as part of testing system.
// Tests all possible states of counter.
// Tests reset.
// 
// Author(s):
// Krista Holden
// Cody Ohlsen
//
//----------------------------------------------------------- 

module SynchronousDownSchematicTester (rst, clk, out);
	input [3:0] out;
	output reg clk, rst;

  parameter stimDelay = 20;

  always begin
    #stimDelay clk = !clk;
  end
  
  initial // Response
  begin
    $display("\t\t out \t rst \t clk \t Time ");
	$monitor("\t\t %b \t %b \t %b", out, rst, clk, $time );
  end

  initial // Stimulus
  begin
    rst = 0; clk = 0;
    #(5 * stimDelay) rst = 1;
    #(64 * stimDelay) rst = 0;
    #(3 * stimDelay) rst = 1;
    #(4 * stimDelay); // needed to see END of simulation
    $finish; // finish simulation
  end
endmodule

Lab1/DownCounterSchematic/ClockDividerSchem.sv
module ClockDividerSchem (clock, out);
	 input clock;
	 output wire out;
	 reg [31:0] divided_clocks;

	 initial
	 divided_clocks = 0;

	 always @(posedge clock)
	 divided_clocks = divided_clocks + 1;
	 
	 parameter whichClock = 10;
	 assign out = divided_clocks[whichClock];
endmodule

Lab1/DownCounterSchematic/flipflop.v
module DFlipFlop(q, qBar, D, clk, rst);
	input D, clk, rst;
	output q, qBar;
	reg q;
	not n1 (qBar, q);
		always@ (posedge clk) // Reset needs to be synchronous
		begin  // Statements need to be non-blocking
			if(rst)
				q <= D;
			else
				q <= 0;
		end
endmodule

Lab1/DownCounterSchematic/DownCounterSchematic.v
// Copyright (C) 1991-2014 Altera Corporation. All rights reserved.
// Your use of Altera Corporation's design tools, logic functions 
// and other software and tools, and its AMPP partner logic 
// functions, and any output files from any of the foregoing 
// (including device programming or simulation files), and any 
// associated documentation or information are expressly subject 
// to the terms and conditions of the Altera Program License 
// Subscription Agreement, the Altera Quartus II License Agreement,
// the Altera MegaCore Function License Agreement, or other 
// applicable license agreement, including, without limitation, 
// that your use is for the sole purpose of programming logic 
// devices manufactured by Altera and sold by Altera or its 
// authorized distributors.  Please refer to the applicable 
// agreement for further details.

// PROGRAM		"Quartus II 64-Bit"
// VERSION		"Version 14.0.0 Build 200 06/17/2014 SJ Full Version"
// CREATED		"Mon Apr 06 17:05:57 2015"

`include "flipflop.v"
`include "ClockDividerSchem.sv"

module DownCounterSchematic(
	rst, clk, out
);

input wire clk, rst;
output wire [3:0] out;

//wire	PIN_AB12;
//wire	PIN_AF14;

//wire	SYNTHESIZED_WIRE_28;
wire	SYNTHESIZED_WIRE_1;
//wire	SYNTHESIZED_WIRE_29;
//wire	SYNTHESIZED_WIRE_30;
wire	SYNTHESIZED_WIRE_31;
wire	SYNTHESIZED_WIRE_32;
wire	SYNTHESIZED_WIRE_9;
wire	SYNTHESIZED_WIRE_10;
//wire	SYNTHESIZED_WIRE_33;
wire	SYNTHESIZED_WIRE_15;
wire	SYNTHESIZED_WIRE_18;
wire	SYNTHESIZED_WIRE_19;
wire	SYNTHESIZED_WIRE_20;
//wire	SYNTHESIZED_WIRE_34;
wire	SYNTHESIZED_WIRE_22;
wire	SYNTHESIZED_WIRE_24;
wire	SYNTHESIZED_WIRE_26;


//assign PIN_AF14 = clk;
//assign SYNTHESIZED_WIRE_34 = clk;
//assign PIN_AB12 = rst;

//assign	out[3] = SYNTHESIZED_WIRE_33;
//assign	out[2] = SYNTHESIZED_WIRE_30;
//assign	out[1] = SYNTHESIZED_WIRE_29;
//assign	out[0] = SYNTHESIZED_WIRE_28;







assign	SYNTHESIZED_WIRE_31 = out[1] | out[0]; // SYNTHESIZED_WIRE_29 | SYNTHESIZED_WIRE_28;

assign	SYNTHESIZED_WIRE_10 = SYNTHESIZED_WIRE_31 & out[2]; // SYNTHESIZED_WIRE_30;

assign	SYNTHESIZED_WIRE_32 = SYNTHESIZED_WIRE_31 | out[2]; // SYNTHESIZED_WIRE_30;

assign	SYNTHESIZED_WIRE_9 =  ~SYNTHESIZED_WIRE_32;

assign	SYNTHESIZED_WIRE_24 = SYNTHESIZED_WIRE_9 | SYNTHESIZED_WIRE_10;

assign	SYNTHESIZED_WIRE_15 = SYNTHESIZED_WIRE_32 | out[3]; // SYNTHESIZED_WIRE_33;

assign	SYNTHESIZED_WIRE_18 = SYNTHESIZED_WIRE_32 & out[3]; // SYNTHESIZED_WIRE_33 ;

assign	SYNTHESIZED_WIRE_19 =  ~SYNTHESIZED_WIRE_15;


/*ClockDividerSchem	b2v_inst2(
	.clock(PIN_AF14),
	.out(SYNTHESIZED_WIRE_34));
	defparam	b2v_inst2.whichClock = 20;*/

assign	SYNTHESIZED_WIRE_1 = out[1] ^ out[0]; // SYNTHESIZED_WIRE_29 ^ SYNTHESIZED_WIRE_28;

assign	SYNTHESIZED_WIRE_26 = SYNTHESIZED_WIRE_18 | SYNTHESIZED_WIRE_19;



assign	SYNTHESIZED_WIRE_20 =  ~out[0]; // ~SYNTHESIZED_WIRE_28;

DFlipFlop	b2v_inst3(
	.D(SYNTHESIZED_WIRE_20),
	//.clk(SYNTHESIZED_WIRE_34),
	.clk(clk),
	//.rst(PIN_AB12),
	.rst(rst),
	//.q(SYNTHESIZED_WIRE_28)
	.q(out[0])
	);

assign	SYNTHESIZED_WIRE_22 =  ~SYNTHESIZED_WIRE_1;

DFlipFlop	b2v_inst4(
	.D(SYNTHESIZED_WIRE_22),
	//.clk(SYNTHESIZED_WIRE_34),
	.clk(clk),
	//.rst(PIN_AB12),
	.rst(rst),
	//.q(SYNTHESIZED_WIRE_29)
	.q(out[1])
	);


DFlipFlop	b2v_inst5(
	.D(SYNTHESIZED_WIRE_24),
	//.clk(SYNTHESIZED_WIRE_34),
	.clk(clk),
	//.rst(PIN_AB12),
	.rst(rst),
	//.q(SYNTHESIZED_WIRE_30)
	.q(out[2])
	);


DFlipFlop	b2v_inst6(
	.D(SYNTHESIZED_WIRE_26),
	//.clk(SYNTHESIZED_WIRE_34),
	.clk(clk),
	//.rst(PIN_AB12),
	.rst(rst),
	//.q(SYNTHESIZED_WIRE_33)
	.q(out[3]) 
	);


endmodule

Lab1/DownCounterSchematic/synchronousDownSchematicTop.v
//-----------------------------------------------------------
// Module name:
// testBench
//
// Description:
// Module implemented as part of testing system.
// Test synchronous down counter with Tester module.
// 
// Author(s):
// Zach Nehrenburg
// Cody Ohlsen
// Krista Holden
//-----------------------------------------------------------

`include "DownCounterSchematic.v"
`include "synchronousDownSchematicTester.v"

module testBench;
	wire rst, clk;
	wire [3:0] out;
	
	//declare instance of synchronous down counter.
	DownCounterSchematic mySynchronousDown (rst, 
											clk, 
											out);
										
	// declare an instance of the Tester module
	SynchronousDownSchematicTester aTester (rst, clk, out);

	// generate file for gtkwave
	initial
	begin
		$dumpfile("mySynchronousDownSchematic.vcd");
		$dumpvars(1,mySynchronousDown);
	end
endmodule

Lab1/DownCounterSchematic/mySynchronousDownSchematic.vcd
$date
	Tue Apr 07 16:09:33 2015
$end
$version
	Icarus Verilog
$end
$timescale
	1s
$end
$scope module testBench $end
$scope module mySynchronousDown $end
$var wire 1 ! SYNTHESIZED_WIRE_1 $end
$var wire 1 " SYNTHESIZED_WIRE_10 $end
$var wire 1 # SYNTHESIZED_WIRE_15 $end
$var wire 1 $ SYNTHESIZED_WIRE_18 $end
$var wire 1 % SYNTHESIZED_WIRE_19 $end
$var wire 1 & SYNTHESIZED_WIRE_20 $end
$var wire 1 ' SYNTHESIZED_WIRE_22 $end
$var wire 1 ( SYNTHESIZED_WIRE_24 $end
$var wire 1 ) SYNTHESIZED_WIRE_26 $end
$var wire 1 * SYNTHESIZED_WIRE_31 $end
$var wire 1 + SYNTHESIZED_WIRE_32 $end
$var wire 1 , SYNTHESIZED_WIRE_9 $end
$var wire 1 - clk $end
$var wire 4 . out [3:0] $end
$var wire 1 / rst $end
$upscope $end
$upscope $end
$enddefinitions $end
#0
$dumpvars
0/
bx .
0-
x,
x+
x*
x)
x(
x'
x&
x%
x$
x#
x"
x!
$end
#20
1)
1(
1%
1,
0#
0+
1'
1&
0*
0!
0"
0$
b0 .
1-
#40
0-
#60
1-
#80
0-
#100
1"
0,
1$
0%
0&
1*
1+
1#
b1111 .
1-
1/
#120
0-
#140
0'
1!
1&
b1110 .
1-
#160
0-
#180
0&
b1101 .
1-
#200
0-
#220
0(
0"
1'
0*
0!
1&
b1100 .
1-
#240
0-
#260
0(
1)
0,
1$
0&
1*
1+
b1011 .
1-
#280
0-
#300
0'
1!
1&
b1010 .
1-
#320
0-
#340
0&
b1001 .
1-
#360
0-
#380
1(
0)
1,
0$
0+
1'
0*
0!
1&
b1000 .
1-
#400
0-
#420
0)
1"
0,
0%
0&
1*
1+
1#
b111 .
1-
#440
0-
#460
0'
1!
1&
b110 .
1-
#480
0-
#500
0&
b101 .
1-
#520
0-
#540
0(
0"
1'
0*
0!
1&
b100 .
1-
#560
0-
#580
0)
0(
0%
0,
1#
0&
1*
1+
b11 .
1-
#600
0-
#620
0'
1!
1&
b10 .
1-
#640
0-
#660
0&
b1 .
1-
#680
0-
#700
1)
1(
1%
1,
0#
0+
1'
0*
0!
1&
b0 .
1-
#720
0-
#740
1"
0,
1$
0%
0&
1*
1+
1#
b1111 .
1-
#760
0-
#780
0'
1!
1&
b1110 .
1-
#800
0-
#820
0&
b1101 .
1-
#840
0-
#860
0(
0"
1'
0*
0!
1&
b1100 .
1-
#880
0-
#900
0(
1)
0,
1$
0&
1*
1+
b1011 .
1-
#920
0-
#940
0'
1!
1&
b1010 .
1-
#960
0-
#980
0&
b1001 .
1-
#1000
0-
#1020
1(
0)
1,
0$
0+
1'
0*
0!
1&
b1000 .
1-
#1040
0-
#1060
0)
1"
0,
0%
0&
1*
1+
1#
b111 .
1-
#1080
0-
#1100
0'
1!
1&
b110 .
1-
#1120
0-
#1140
0&
b101 .
1-
#1160
0-
#1180
0(
0"
1'
0*
0!
1&
b100 .
1-
#1200
0-
#1220
0)
0(
0%
0,
1#
0&
1*
1+
b11 .
1-
#1240
0-
#1260
0'
1!
1&
b10 .
1-
#1280
0-
#1300
0&
b1 .
1-
#1320
0-
#1340
1)
1(
1%
1,
0#
0+
1'
0*
0!
1&
b0 .
1-
#1360
0-
#1380
1-
0/
#1400
0-
#1420
1-
#1440
0-
1/
#1460
1"
0,
1$
0%
0&
1*
1+
1#
b1111 .
1-
#1480
0-
#1500
0'
1!
1&
b1110 .
1-
