Lab1/DownCounterSchematic/synchronousDownSchematicTester.v
//-----------------------------------------------------------
// Module name:
// SynchronousDownTester
//
// Description:
// Module implemented as part of testing system.
// Tests all possible states of counter.
// Tests reset.
// 
// Author(s):
// Krista Holden
// Cody Ohlsen
//
//----------------------------------------------------------- 

module SynchronousDownSchematicTester (rst, clk, out);
	input [3:0] out;
	output reg clk, rst;

  parameter stimDelay = 20;

  always begin
    #stimDelay clk = !clk;
  end
  
  initial // Response
  begin
    $display("\t\t out \t rst \t clk \t Time ");
	$monitor("\t\t %b \t %b \t %b", out, rst, clk, $time );
  end

  initial // Stimulus
  begin
    rst = 0; clk = 0;
    #stimDelay rst = 1;
    #(64 * stimDelay) rst = 0;
    #(3 * stimDelay) rst = 1;
    #(4*stimDelay); // needed to see END of simulation
    $finish; // finish simulation
  end
endmodule

Lab1/DownCounterSchematic/ClockDividerSchem.sv
module ClockDividerSchem (clock, out);
	 input clock;
	 output wire out;
	 reg [31:0] divided_clocks;

	 initial
	 divided_clocks = 0;

	 always @(posedge clock)
	 divided_clocks = divided_clocks + 1;
	 
	 parameter whichClock = 10;
	 assign out = divided_clocks[whichClock];
endmodule

Lab1/DownCounterSchematic/flipflop.v
module DFlipFlop(q, qBar, D, clk, rst);
	input D, clk, rst;
	output q, qBar;
	reg q;
	not n1 (qBar, q);
		always@ (posedge clk) // Reset needs to be synchronous
		begin  // Statements need to be non-blocking
			if(rst)
				q <= D;
			else
				q <= 0;
		end
endmodule

Lab1/DownCounterSchematic/DownCounterSchematic.v
// Copyright (C) 1991-2014 Altera Corporation. All rights reserved.
// Your use of Altera Corporation's design tools, logic functions 
// and other software and tools, and its AMPP partner logic 
// functions, and any output files from any of the foregoing 
// (including device programming or simulation files), and any 
// associated documentation or information are expressly subject 
// to the terms and conditions of the Altera Program License 
// Subscription Agreement, the Altera Quartus II License Agreement,
// the Altera MegaCore Function License Agreement, or other 
// applicable license agreement, including, without limitation, 
// that your use is for the sole purpose of programming logic 
// devices manufactured by Altera and sold by Altera or its 
// authorized distributors.  Please refer to the applicable 
// agreement for further details.

// PROGRAM		"Quartus II 64-Bit"
// VERSION		"Version 14.0.0 Build 200 06/17/2014 SJ Full Version"
// CREATED		"Mon Apr 06 17:05:57 2015"

`include "flipflop.v"
`include "ClockDividerSchem.sv"

module DownCounterSchematic(
	rst, clk, out
);

input wire clk, rst;
output wire [3:0] out;

wire	PIN_AB12;
wire	PIN_AF14;

wire	SYNTHESIZED_WIRE_28;
wire	SYNTHESIZED_WIRE_1;
wire	SYNTHESIZED_WIRE_29;
wire	SYNTHESIZED_WIRE_30;
wire	SYNTHESIZED_WIRE_31;
wire	SYNTHESIZED_WIRE_32;
wire	SYNTHESIZED_WIRE_9;
wire	SYNTHESIZED_WIRE_10;
wire	SYNTHESIZED_WIRE_33;
wire	SYNTHESIZED_WIRE_15;
wire	SYNTHESIZED_WIRE_18;
wire	SYNTHESIZED_WIRE_19;
wire	SYNTHESIZED_WIRE_20;
wire	SYNTHESIZED_WIRE_34;
wire	SYNTHESIZED_WIRE_22;
wire	SYNTHESIZED_WIRE_24;
wire	SYNTHESIZED_WIRE_26;


assign PIN_AF14 = clk;
assign SYNTHESIZED_WIRE_34 = clk;
assign PIN_AB12 = rst;

assign	out[0] = SYNTHESIZED_WIRE_33;
assign	out[1] = SYNTHESIZED_WIRE_30;
assign	out[2] = SYNTHESIZED_WIRE_29;
assign	out[3] = SYNTHESIZED_WIRE_28;



assign	SYNTHESIZED_WIRE_20 =  ~SYNTHESIZED_WIRE_28;

assign	SYNTHESIZED_WIRE_22 =  ~SYNTHESIZED_WIRE_1;

assign	SYNTHESIZED_WIRE_31 = SYNTHESIZED_WIRE_29 | SYNTHESIZED_WIRE_28;

assign	SYNTHESIZED_WIRE_10 = SYNTHESIZED_WIRE_30 & SYNTHESIZED_WIRE_31;

assign	SYNTHESIZED_WIRE_32 = SYNTHESIZED_WIRE_31 | SYNTHESIZED_WIRE_30;

assign	SYNTHESIZED_WIRE_9 =  ~SYNTHESIZED_WIRE_32;

assign	SYNTHESIZED_WIRE_24 = SYNTHESIZED_WIRE_9 | SYNTHESIZED_WIRE_10;

assign	SYNTHESIZED_WIRE_15 = SYNTHESIZED_WIRE_32 | SYNTHESIZED_WIRE_33;

assign	SYNTHESIZED_WIRE_18 = SYNTHESIZED_WIRE_33 & SYNTHESIZED_WIRE_32;

assign	SYNTHESIZED_WIRE_19 =  ~SYNTHESIZED_WIRE_15;


/*ClockDividerSchem	b2v_inst2(
	.clock(PIN_AF14),
	.out(SYNTHESIZED_WIRE_34));
	defparam	b2v_inst2.whichClock = 20;

assign	SYNTHESIZED_WIRE_1 = SYNTHESIZED_WIRE_29 ^ SYNTHESIZED_WIRE_28;

assign	SYNTHESIZED_WIRE_26 = SYNTHESIZED_WIRE_18 | SYNTHESIZED_WIRE_19;*/


DFlipFlop	b2v_inst3(
	.D(SYNTHESIZED_WIRE_20),
	.clk(SYNTHESIZED_WIRE_34),
	.rst(PIN_AB12),
	.q(SYNTHESIZED_WIRE_28)
	);


DFlipFlop	b2v_inst4(
	.D(SYNTHESIZED_WIRE_22),
	.clk(SYNTHESIZED_WIRE_34),
	.rst(PIN_AB12),
	.q(SYNTHESIZED_WIRE_29)
	);


DFlipFlop	b2v_inst5(
	.D(SYNTHESIZED_WIRE_24),
	.clk(SYNTHESIZED_WIRE_34),
	.rst(PIN_AB12),
	.q(SYNTHESIZED_WIRE_30)
	);


DFlipFlop	b2v_inst6(
	.D(SYNTHESIZED_WIRE_26),
	.clk(SYNTHESIZED_WIRE_34),
	.rst(PIN_AB12),
	.q(SYNTHESIZED_WIRE_33)
	);


endmodule

Lab1/DownCounterSchematic/synchronousDownSchematicTop.v
//-----------------------------------------------------------
// Module name:
// testBench
//
// Description:
// Module implemented as part of testing system.
// Test synchronous down counter with Tester module.
// 
// Author(s):
// Zach Nehrenburg
// Cody Ohlsen
// Krista Holden
//-----------------------------------------------------------

`include "DownCounterSchematic.v"
`include "synchronousDownSchematicTester.v"

module testBench;
	wire rst, clk;
	wire [3:0] out;
	
	//declare instance of synchronous down counter.
	DownCounterSchematic mySynchronousDown (rst, 
											clk, 
											out);
										
	// declare an instance of the Tester module
	SynchronousDownSchematicTester aTester (rst, clk, out);

	// generate file for gtkwave
	initial
	begin
		$dumpfile("mySynchronousDownSchematic.vcd");
		$dumpvars(1,mySynchronousDown);
	end
endmodule

Lab1/DownCounterSchematic/mySynchronousDownSchematic.vcd
$date
	Tue Apr 07 15:22:26 2015
$end
$version
	Icarus Verilog
$end
$timescale
	1s
$end
$scope module testBench $end
$scope module mySynchronousDown $end
$var wire 1 ! PIN_AB12 $end
$var wire 1 " PIN_AF14 $end
$var wire 1 # SYNTHESIZED_WIRE_1 $end
$var wire 1 $ SYNTHESIZED_WIRE_10 $end
$var wire 1 % SYNTHESIZED_WIRE_15 $end
$var wire 1 & SYNTHESIZED_WIRE_18 $end
$var wire 1 ' SYNTHESIZED_WIRE_19 $end
$var wire 1 ( SYNTHESIZED_WIRE_20 $end
$var wire 1 ) SYNTHESIZED_WIRE_22 $end
$var wire 1 * SYNTHESIZED_WIRE_24 $end
$var wire 1 + SYNTHESIZED_WIRE_26 $end
$var wire 1 , SYNTHESIZED_WIRE_28 $end
$var wire 1 - SYNTHESIZED_WIRE_29 $end
$var wire 1 . SYNTHESIZED_WIRE_30 $end
$var wire 1 / SYNTHESIZED_WIRE_31 $end
$var wire 1 0 SYNTHESIZED_WIRE_32 $end
$var wire 1 1 SYNTHESIZED_WIRE_33 $end
$var wire 1 2 SYNTHESIZED_WIRE_34 $end
$var wire 1 3 SYNTHESIZED_WIRE_9 $end
$var wire 1 4 clk $end
$var wire 4 5 out [3:0] $end
$var wire 1 6 rst $end
$upscope $end
$upscope $end
$enddefinitions $end
#0
$dumpvars
06
b0 5
04
13
02
01
00
0/
0.
0-
0,
z+
1*
x)
1(
1'
0&
0%
0$
z#
0"
0!
$end
#20
0'
03
x&
1%
10
1$
1/
0(
z1
1.
x-
1,
b1x1z 5
1!
16
12
1"
14
#40
02
0"
04
#60
x*
x$
x/
1(
0,
b0x1z 5
12
1"
14
#80
02
0"
04
#100
1/
0(
x.
1,
b1xxz 5
12
1"
14
#120
02
0"
04
#140
x'
x3
x%
x0
x/
1(
0,
b0xxz 5
12
1"
14
#160
02
0"
04
#180
0'
03
1%
10
1/
0(
1,
b1xxz 5
12
1"
14
#200
02
0"
04
#220
x'
x3
x%
x0
x/
1(
0,
b0xxz 5
12
1"
14
#240
02
0"
04
#260
0'
03
1%
10
1/
0(
1,
b1xxz 5
12
1"
14
#280
02
0"
04
#300
x'
x3
x%
x0
x/
1(
0,
b0xxz 5
12
1"
14
#320
02
0"
04
#340
0'
03
1%
10
1/
0(
1,
b1xxz 5
12
1"
14
#360
02
0"
04
#380
x'
x3
x%
x0
x/
1(
0,
b0xxz 5
12
1"
14
#400
02
0"
04
#420
0'
03
1%
10
1/
0(
1,
b1xxz 5
12
1"
14
#440
02
0"
04
#460
x'
x3
x%
x0
x/
1(
0,
b0xxz 5
12
1"
14
#480
02
0"
04
#500
0'
03
1%
10
1/
0(
1,
b1xxz 5
12
1"
14
#520
02
0"
04
#540
x'
x3
x%
x0
x/
1(
0,
b0xxz 5
12
1"
14
#560
02
0"
04
#580
0'
03
1%
10
1/
0(
1,
b1xxz 5
12
1"
14
#600
02
0"
04
#620
x'
x3
x%
x0
x/
1(
0,
b0xxz 5
12
1"
14
#640
02
0"
04
#660
0'
03
1%
10
1/
0(
1,
b1xxz 5
12
1"
14
#680
02
0"
04
#700
x'
x3
x%
x0
x/
1(
0,
b0xxz 5
12
1"
14
#720
02
0"
04
#740
0'
03
1%
10
1/
0(
1,
b1xxz 5
12
1"
14
#760
02
0"
04
#780
x'
x3
x%
x0
x/
1(
0,
b0xxz 5
12
1"
14
#800
02
0"
04
#820
0'
03
1%
10
1/
0(
1,
b1xxz 5
12
1"
14
#840
02
0"
04
#860
x'
x3
x%
x0
x/
1(
0,
b0xxz 5
12
1"
14
#880
02
0"
04
#900
0'
03
1%
10
1/
0(
1,
b1xxz 5
12
1"
14
#920
02
0"
04
#940
x'
x3
x%
x0
x/
1(
0,
b0xxz 5
12
1"
14
#960
02
0"
04
#980
0'
03
1%
10
1/
0(
1,
b1xxz 5
12
1"
14
#1000
02
0"
04
#1020
x'
x3
x%
x0
x/
1(
0,
b0xxz 5
12
1"
14
#1040
02
0"
04
#1060
0'
03
1%
10
1/
0(
1,
b1xxz 5
12
1"
14
#1080
02
0"
04
#1100
x'
x3
x%
x0
x/
1(
0,
b0xxz 5
12
1"
14
#1120
02
0"
04
#1140
0'
03
1%
10
1/
0(
1,
b1xxz 5
12
1"
14
#1160
02
0"
04
#1180
x'
x3
x%
x0
x/
1(
0,
b0xxz 5
12
1"
14
#1200
02
0"
04
#1220
0'
03
1%
10
1/
0(
1,
b1xxz 5
12
1"
14
#1240
02
0"
04
#1260
x'
x3
x%
x0
x/
1(
0,
b0xxz 5
12
1"
14
#1280
02
0"
04
#1300
1*
1'
13
0&
0%
00
0$
0/
01
0.
0-
b0 5
12
1"
14
0!
06
#1320
02
0"
04
#1340
12
1"
14
#1360
02
0"
04
1!
16
#1380
0'
03
x&
1%
10
1$
1/
0(
z1
1.
x-
1,
b1x1z 5
12
1"
14
#1400
02
0"
04
#1420
x*
x$
x/
1(
0,
b0x1z 5
12
1"
14
#1440
02
0"
04
